odoo10_addon_pos_default_empty_image-10.0.1.0.1-py3.8-nspkg.pth
odoo/addons/pos_default_empty_image/README.rst
odoo/addons/pos_default_empty_image/__init__.py
odoo/addons/pos_default_empty_image/__manifest__.py
odoo/addons/pos_default_empty_image/i18n/ca.po
odoo/addons/pos_default_empty_image/i18n/es.po
odoo/addons/pos_default_empty_image/i18n/pos_default_empty_image.pot
odoo/addons/pos_default_empty_image/models/__init__.py
odoo/addons/pos_default_empty_image/models/product_product.py
odoo/addons/pos_default_empty_image/static/description/icon.png
odoo/addons/pos_default_empty_image/static/description/pos_display_default.png
odoo/addons/pos_default_empty_image/static/description/pos_display_improved.png
odoo/addons/pos_default_empty_image/static/src/css/pos_default_empty_image.css
odoo/addons/pos_default_empty_image/static/src/js/db.js
odoo/addons/pos_default_empty_image/static/src/js/widgets.js
odoo/addons/pos_default_empty_image/static/src/xml/pos_default_empty_image.xml
odoo/addons/pos_default_empty_image/views/templates.xml
odoo10_addon_pos_default_empty_image-10.0.1.0.1.dist-info/METADATA
odoo10_addon_pos_default_empty_image-10.0.1.0.1.dist-info/WHEEL
odoo10_addon_pos_default_empty_image-10.0.1.0.1.dist-info/namespace_packages.txt
odoo10_addon_pos_default_empty_image-10.0.1.0.1.dist-info/top_level.txt
odoo10_addon_pos_default_empty_image-10.0.1.0.1.dist-info/RECORD
